odoo/addons/ssi_helpdesk_work_log/README.rst
odoo/addons/ssi_helpdesk_work_log/__init__.py
odoo/addons/ssi_helpdesk_work_log/__manifest__.py
odoo/addons/ssi_helpdesk_work_log/models/__init__.py
odoo/addons/ssi_helpdesk_work_log/models/helpdesk_communication.py
odoo/addons/ssi_helpdesk_work_log/models/helpdesk_ticket.py
odoo/addons/ssi_helpdesk_work_log/models/helpdesk_type.py
odoo/addons/ssi_helpdesk_work_log/models/helpdesk_type_category.py
odoo/addons/ssi_helpdesk_work_log/static/description/icon.png
odoo/addons/ssi_helpdesk_work_log/views/helpdesk_type_category_views.xml
odoo/addons/ssi_helpdesk_work_log/views/helpdesk_type_views.xml
odoo/addons/ssi_helpdesk_work_log/wizards/__init__.py
odoo/addons/ssi_helpdesk_work_log/wizards/create_ticket_from_communication.py
odoo/addons/ssi_helpdesk_work_log/wizards/split_helpdesk_ticket.py
odoo14_addon_ssi_helpdesk_work_log-14.0.1.3.0.dist-info/METADATA
odoo14_addon_ssi_helpdesk_work_log-14.0.1.3.0.dist-info/WHEEL
odoo14_addon_ssi_helpdesk_work_log-14.0.1.3.0.dist-info/top_level.txt
odoo14_addon_ssi_helpdesk_work_log-14.0.1.3.0.dist-info/RECORD
